PFAS_SAT/MCResults.py
PFAS_SAT/ProcessModelsMetaData.py
PFAS_SAT/Project.py
PFAS_SAT/__init__.py
PFAS_SAT/utils.py
PFAS_SAT/GUI/HelpGuide_ui.py
PFAS_SAT/GUI/MC_ui.py
PFAS_SAT/GUI/PFAS_SAT_rc.py
PFAS_SAT/GUI/PFAS_SAT_run.py
PFAS_SAT/GUI/PFAS_SAT_ui.py
PFAS_SAT/GUI/Reference_ui.py
PFAS_SAT/GUI/SA_ui.py
PFAS_SAT/GUI/Setting_ui.py
PFAS_SAT/GUI/Table_from_pandas.py
PFAS_SAT/GUI/Workers.py
PFAS_SAT/GUI/__init__.py
PFAS_SAT-0.3.1.dist-info/AUTHORS.rst
PFAS_SAT-0.3.1.dist-info/LICENSE.md
PFAS_SAT-0.3.1.dist-info/METADATA
PFAS_SAT-0.3.1.dist-info/WHEEL
PFAS_SAT-0.3.1.dist-info/top_level.txt
PFAS_SAT-0.3.1.dist-info/RECORD
