Metadata-Version: 2.1
Name: PFAS-SAT
Version: 0.3.1
Summary: Perfluoroalkyl Substances Systems Analysis Tool (PFAS_SAT)
Home-page: https://github.com/PFAS-SAT/PFAS-SAT
Author: Mojtaba Sardarmehni
Author-email: msardar2@ncsu.edu
License: GNU GENERAL PUBLIC LICENSE V2
Keywords: PFAS_SAT
Platform: UNKNOWN
Classifier: Development Status :: 3 - Alpha
Classifier: Intended Audience :: Education
Classifier: Intended Audience :: Science/Research
Classifier: License :: OSI Approved :: GNU General Public License v2 (GPLv2)
Classifier: Natural Language :: English
Classifier: Programming Language :: Python :: 3.7
Classifier: Operating System :: MacOS :: MacOS X
Classifier: Operating System :: Microsoft :: Windows
Classifier: Topic :: Scientific/Engineering :: Information Analysis
Classifier: Topic :: Scientific/Engineering :: Mathematics
Classifier: Topic :: Scientific/Engineering :: Visualization
Classifier: Natural Language :: English
Requires-Python: >=3.7
Requires-Dist: PFAS-SAT-InputData
Requires-Dist: PFAS-SAT-ProcessModels
Requires-Dist: jupyter
Requires-Dist: pandas
Requires-Dist: stats-arrays
Requires-Dist: PySide2 (==5.14)
Requires-Dist: plotly
Requires-Dist: graphviz
Requires-Dist: matplotlib
Requires-Dist: seaborn
